[
  {
    "rank": 1,
    "id": 1596291,
    "title": "Queen of Chess",
    "poster_path": "/ag5TZNcK3vHdCCpZIY8syjwzgfr.jpg",
    "backdrop_path": "/y5haKgSz1hCDatwIOMuqZ1CFKPW.jpg",
    "popularity": 19.8735,
    "file": "01-queen-of-chess-1596291.jpg"
  },
  {
    "rank": 2,
    "id": 884193,
    "title": "The Poet’s Wife",
    "poster_path": "/hyIRxCOuvHbvo9P5v3hmgnvUdv1.jpg",
    "backdrop_path": null,
    "popularity": 14.9645,
    "file": "02-the-poet-s-wife-884193.jpg"
  },
  {
    "rank": 3,
    "id": 537971,
    "title": "Mia",
    "poster_path": "/nEmw1fZOQp2qFGdrak3ipCbe31G.jpg",
    "backdrop_path": "/vTcJyuk0uJLKEPCrjJTB2zzY7Np.jpg",
    "popularity": 11.9439,
    "file": "03-mia-537971.jpg"
  },
  {
    "rank": 4,
    "id": 1620991,
    "title": "The Investigation of Lucy Letby",
    "poster_path": "/qhNThwc72GqihJhXaP29Af5hJ2A.jpg",
    "backdrop_path": "/qhSfXdkrIzwYsyQ3Z9ehFmO3zjy.jpg",
    "popularity": 11.9113,
    "file": "04-the-investigation-of-lucy-letby-1620991.jpg"
  }
]